config.yml
overturemapsdownloader/__init__.py
overturemapsdownloader/config.py
overturemapsdownloader/dask_qrys.py
overturemapsdownloader/main.py
overturemapsdownloader/om_logic.py
overturemapsdownloader/read_om_schemas.py
overturemapsdownloader/utils_helper.py
overturemapsdownloader/yaml_helper.py
overturemapsdownloader-0.1.9.dist-info/LICENSE
overturemapsdownloader-0.1.9.dist-info/METADATA
overturemapsdownloader-0.1.9.dist-info/WHEEL
overturemapsdownloader-0.1.9.dist-info/entry_points.txt
overturemapsdownloader-0.1.9.dist-info/RECORD
