Metadata-Version: 2.1
Name: overturemapsdownloader
Version: 0.1.9
Summary: Overture Maps Downloader simplifies geospatial data manipulation
Author: Youssef-Harby
Author-email: me@youssefharby.com
Requires-Python: >=3.10,<4.0
Classifier: Programming Language :: Python :: 3
Classifier: Programming Language :: Python :: 3.10
Classifier: Programming Language :: Python :: 3.11
Provides-Extra: gdal-support
Requires-Dist: adlfs (>=2024.4.0,<2025.0.0)
Requires-Dist: dask-geopandas (>=0.3.1,<0.4.0)
Requires-Dist: dask[complete,dataframe] (>=2024.4.1,<2025.0.0)
Requires-Dist: duckdb (>=0.10.1,<0.11.0)
Requires-Dist: fastparquet (>=2024.2.0,<2025.0.0)
Requires-Dist: fiona (>=1.9.6,<2.0.0)
Requires-Dist: gdal (==3.8.5) ; extra == "gdal-support"
Requires-Dist: geopandas (>=0.14.3,<0.15.0)
Requires-Dist: jupyter (>=1.0.0,<2.0.0)
Requires-Dist: pyarrow (>=15.0.2,<16.0.0)
Requires-Dist: pyproj (>=3.6.1,<4.0.0)
Requires-Dist: s3fs (>=2024.3.1,<2025.0.0)
Requires-Dist: shapely (>=2.0.4,<3.0.0)
Requires-Dist: typer[all] (>=0.12.3,<0.13.0)
